{
    "polls": [
        {
            "id": "707292302363590777",
            "poll": {
                "title": "test",
                "author": "zackkomo",
                "channel": "419630937773441028",
                "options": [
                    "1️⃣  1"
                ],
                "description": "To re-access this poll use the command !pollCheck 0",
                "mes": "```\nPoll by zackkomo\ntest\n1️⃣  1  \n---------\n```",
                "votes": [
                    []
                ]
            }
        },
        null
    ],
    "pollCount": 0
}